{
    "AnimalsAndCoinsIsland250": {
        "nameId": "AnimalsAndCoinsIsland250",
    },
     "TwitterLikePost4": {
        "nameId": "TwitterLikePost4",
    },
     "TON%20Fest%20X%20follow": {
        "nameId": "TON%20Fest%20X%20follow",
    },
     "TON%20Fest%20X%20follow": {
        "nameId": "TON%20Fest%20X%20follow",
    },
     "twitterQuotePost69": {
        "nameId": "twitterQuotePost69",
    },
     "twitterLikeShitcoinaire13": {
        "nameId": "twitterLikeShitcoinaire13",
    },
     "TON%20Fest%20tg%20channel": {
        "nameId": "TON%20Fest%20tg%20channel",
    },
     "KittVerse": {
        "nameId": "KittVerse",
    },
     "JoinDuckMyDuck": {
        "nameId": "JoinDuckMyDuck",
    },
     "Mouse%20Homies": {
        "nameId": "Mouse%20Homies",
    },
     "playGenkiMiner2": {
        "nameId": "playGenkiMiner2",
    },
     "joinTsubasaQuest": {
        "nameId": "joinTsubasaQuest",
    },
     "JoinKrypton": {
        "nameId": "JoinKrypton",
    },
     "JoinGOATSdec": {
        "nameId": "JoinGOATSdec",
    },
     "JoinMinerQuest1": {
        "nameId": "JoinMinerQuest1",
    },
     "joinFoxCoin1": {
        "nameId": "joinFoxCoin1",
    },
     "PlayDejenDog_3": {
        "nameId": "PlayDejenDog_3",
    },
     "MeshQuest_2": {
        "nameId": "MeshQuest_2",
    },
     "playTabizoo2": {
        "nameId": "playTabizoo2",
    },
     "playPlaydeckBoinkersBooster": {
        "nameId": "playPlaydeckBoinkersBooster",
    },
     "joinMegaMine": {
        "nameId": "joinMegaMine",
    },
     "PlayPookie%20Chase": {
        "nameId": "PlayPookie%20Chase",
    },
     "telegramJoinBoinkersNewsChannel": {
        "nameId": "telegramJoinBoinkersNewsChannel",
    },
    "TON%20Fest%20Ticket": {
        "_id": "6751beb2698fae14cdcfe09d",
        "user": "6700afc019c604ece17d307f",
        "nameId": "TON%20Fest%20Ticket",
        "clickDateTime": "2024-10-08T11:14:24.288Z",
        "claimDateTime": "2024-11-08T04:04:25.598Z",
        "totalGameEnergyAwarded": 600,
        "__v": 0
    },
}
